rtv/__init__.py
rtv/__main__.py
rtv/__version__.py
rtv/clipboard.py
rtv/config.py
rtv/content.py
rtv/docs.py
rtv/exceptions.py
rtv/inbox_page.py
rtv/mime_parsers.py
rtv/oauth.py
rtv/objects.py
rtv/page.py
rtv/submission_page.py
rtv/subreddit_page.py
rtv/subscription_page.py
rtv/terminal.py
rtv/theme.py
rtv/packages/__init__.py
rtv/packages/praw/__init__.py
rtv/packages/praw/decorator_helpers.py
rtv/packages/praw/decorators.py
rtv/packages/praw/errors.py
rtv/packages/praw/handlers.py
rtv/packages/praw/helpers.py
rtv/packages/praw/internal.py
rtv/packages/praw/multiprocess.py
rtv/packages/praw/objects.py
rtv/packages/praw/praw.ini
rtv/packages/praw/settings.py
rtv/templates/index.html
rtv/templates/mailcap
rtv/templates/rtv.cfg
rtv/themes/colorblind-dark.cfg
rtv/themes/default.cfg.example
rtv/themes/molokai.cfg
rtv/themes/papercolor.cfg
rtv/themes/solarized-dark.cfg
rtv/themes/solarized-light.cfg
rtv2-1.27.1.data/data/share/man/man1/rtv.1
rtv2-1.27.1.dist-info/AUTHORS.rst
rtv2-1.27.1.dist-info/LICENSE
rtv2-1.27.1.dist-info/METADATA
rtv2-1.27.1.dist-info/WHEEL
rtv2-1.27.1.dist-info/entry_points.txt
rtv2-1.27.1.dist-info/top_level.txt
rtv2-1.27.1.dist-info/RECORD
